odoo10_addon_crm_meeting_commercial_partner-10.0.1.0.0.99.dev4-py2.7-nspkg.pth
odoo/addons/crm_meeting_commercial_partner/README.rst
odoo/addons/crm_meeting_commercial_partner/__init__.py
odoo/addons/crm_meeting_commercial_partner/__manifest__.py
odoo/addons/crm_meeting_commercial_partner/i18n/crm_meeting_commercial_partner.pot
odoo/addons/crm_meeting_commercial_partner/i18n/de.po
odoo/addons/crm_meeting_commercial_partner/models/__init__.py
odoo/addons/crm_meeting_commercial_partner/models/res_partner.py
odoo/addons/crm_meeting_commercial_partner/static/description/icon.png
odoo/addons/crm_meeting_commercial_partner/tests/__init__.py
odoo/addons/crm_meeting_commercial_partner/tests/test_crm_meeting_commercial_partner.py
odoo10_addon_crm_meeting_commercial_partner-10.0.1.0.0.99.dev4.dist-info/METADATA
odoo10_addon_crm_meeting_commercial_partner-10.0.1.0.0.99.dev4.dist-info/RECORD
odoo10_addon_crm_meeting_commercial_partner-10.0.1.0.0.99.dev4.dist-info/WHEEL
odoo10_addon_crm_meeting_commercial_partner-10.0.1.0.0.99.dev4.dist-info/namespace_packages.txt
odoo10_addon_crm_meeting_commercial_partner-10.0.1.0.0.99.dev4.dist-info/top_level.txt
